[

  {
    "ref": "1",
    "title": "The Last Sacrifice",
    "video": {
      "duration": "3:50",
      "yt": "DrAIET5ykUk"
    }
  },
  {
    "ref": "2",
    "title": "After Suicide Bombing",
    "video": {
      "duration": "3:49",
      "yt": "1t46Y1yve9g"
    }
  },
  {
    "ref": "3",
    "title": "Mage Vanharma",
    "video": {
      "duration": "6:49",
      "yt": "04Pp65ghlKU"
    }
  },
  {
    "ref": "4",
    "title": "Human Emotions",
    "video": {
      "duration": "3:25",
      "yt": "vZzG8GrgQTY"
    }
  },
  {
    "ref": "5",
    "title": "Looking For Taivas",
    "video": {
      "duration": "3:47",
      "yt": "wzytR1_NmWg"
    }
  },
  {
    "ref": "6",
    "title": "The Memorial",
    "video": {
      "duration": "11:22",
      "yt": "U4iU-Rjs9wE"
    }
  }
]
