[
  {
    "ref": "1",
    "title": "Physalis Consciousness",
    "video": {
      "duration": "3:04",
      "yt": "D50V1QBSJUo"
    }
  },
  {
    "ref": "2",
    "title": "Disgusting Soup",
    "video": {
      "duration": "16:40",
      "yt": "tofVC0n9mdY"
    }
  },
  {
    "ref": "3",
    "title": "Rain VS The Emperor",
    "video": {
      "duration": "21:29",
      "yt": "OAFW0WCB5kQ"
    }
  },
  {
    "ref": "4",
    "title": "Life at Stake",
    "video": {
      "duration": "20:01",
      "yt": "X05F9Q2lPug"
    }
  },
  {
    "ref": "5",
    "title": "Telepathy",
    "video": {
      "duration": "20:40",
      "yt": "_ONMIApoiVs"
    }
  },
  {
    "ref": "6",
    "title": "Walk Down the Shining Road",
    "video": {
      "duration": "13:33",
      "yt": "SADPogMxs6g"
    }
  }
]
